vnstockdata/__init__.py
vnstockdata/client.py
vnstockdata/stock.py
vnstockdata/config/__init__.py
vnstockdata/config/config.c
vnstockdata/config/config.cpython-39-darwin.so
vnstockdata/config/config.pyx
vnstockdata/config/ensure_logged_in.c
vnstockdata/config/ensure_logged_in.cpython-39-darwin.so
vnstockdata/config/ensure_logged_in.pyx
vnstockdata/process_client/__init__.py
vnstockdata/process_client/login.c
vnstockdata/process_client/login.cpython-39-darwin.so
vnstockdata/process_stock/__init__.py
vnstockdata/process_stock/ohlcv.c
vnstockdata/process_stock/ohlcv.cpython-39-darwin.so
vnstockdata-1.0.5.dist-info/METADATA
vnstockdata-1.0.5.dist-info/WHEEL
vnstockdata-1.0.5.dist-info/top_level.txt
vnstockdata-1.0.5.dist-info/RECORD
