Metadata-Version: 2.1
Name: vnstockdata
Version: 1.0.5
Summary: Dữ liệu thị trường chứng khoán Việt Nam
Home-page: https://vnstockdata.com
Author: vnstockdata.com
Author-email: support@vnstockdata.com
License: UNKNOWN
Platform: UNKNOWN
Classifier: Programming Language :: Python :: 3
Classifier: License :: OSI Approved :: MIT License
Classifier: Operating System :: OS Independent
Requires-Python: >=3.9
Requires-Dist: pandas==2.1.2
Requires-Dist: requests
